jVMC/__init__.py
jVMC/global_defs.py
jVMC/mpi_wrapper.py
jVMC/sampler.py
jVMC/stats.py
jVMC/version.py
jVMC/vqs.py
jVMC/nets/__init__.py
jVMC/nets/activation_functions.py
jVMC/nets/cnn.py
jVMC/nets/ffn.py
jVMC/nets/initializers.py
jVMC/nets/rbm.py
jVMC/nets/rnn1d_general.py
jVMC/nets/rnn2d_general.py
jVMC/nets/sym_wrapper.py
jVMC/nets/two_nets_wrapper.py
jVMC/operator/__init__.py
jVMC/operator/base.py
jVMC/operator/branch_free.py
jVMC/operator/povm.py
jVMC/util/__init__.py
jVMC/util/minsr.py
jVMC/util/output_manager.py
jVMC/util/stepper.py
jVMC/util/symmetries.py
jVMC/util/tdvp.py
jVMC/util/util.py
jvmc-1.5.8.dist-info/licenses/LICENSE
jvmc-1.5.8.dist-info/METADATA
jvmc-1.5.8.dist-info/WHEEL
jvmc-1.5.8.dist-info/top_level.txt
jvmc-1.5.8.dist-info/RECORD
