Metadata-Version: 2.4
Name: jVMC
Version: 1.5.8
Summary: jVMC: Versatile and performant variational Monte Carlo
Author-email: Markus Schmitt <markus.schmitt@ur.de>
License: MIT License
Project-URL: Documentation, https://jvmc.readthedocs.io/en/latest/#
Project-URL: Repository, https://github.com/markusschmitt/vmc_jax
Project-URL: Issues, https://github.com/markusschmitt/vmc_jax/issues
Keywords: Neural quantum states,Variational Monte Carlo
Classifier: Programming Language :: Python :: 3
Classifier: License :: OSI Approved :: MIT License
Classifier: Operating System :: OS Independent
Requires-Python: >=3.9
License-File: LICENSE
Requires-Dist: numpy>=2
Requires-Dist: openfermion
Requires-Dist: jax<=0.7.2,>=0.4.12
Requires-Dist: jaxlib<=0.7.2,>=0.4.12
Requires-Dist: flax>=0.7.0
Requires-Dist: mpi4py
Requires-Dist: h5py
Requires-Dist: PyYAML
Requires-Dist: matplotlib
Requires-Dist: scipy
Provides-Extra: dev
Requires-Dist: sphinx; extra == "dev"
Requires-Dist: mock; extra == "dev"
Requires-Dist: sphinx_rtd_theme; extra == "dev"
Requires-Dist: pytest; extra == "dev"
Requires-Dist: pytest-mpi; extra == "dev"
Provides-Extra: gpu
Requires-Dist: jax[cuda12]<=0.5.0,>=0.4.12; extra == "gpu"
Dynamic: license-file
